sqlmodel_controller/__init__.py
sqlmodel_controller/connection.py
sqlmodel_controller/controller.py
sqlmodel_controller/dao.py
sqlmodel_controller/model.py
sqlmodel_controller-0.1.8.dist-info/LICENSE
sqlmodel_controller-0.1.8.dist-info/METADATA
sqlmodel_controller-0.1.8.dist-info/WHEEL
sqlmodel_controller-0.1.8.dist-info/top_level.txt
sqlmodel_controller-0.1.8.dist-info/RECORD
