Metadata-Version: 2.1
Name: sqlmodel-controller
Version: 0.1.8
Summary: A Controller Interface for basic CRUD operations with SQLModel/SQLAlchemy
Home-page: https://github.com/0xthiagomartins/sqlmodel-controller
Author: Thiago Martins
Author-email: martins@dmail.ai
Classifier: Development Status :: 3 - Alpha
Classifier: Intended Audience :: Developers
Classifier: License :: OSI Approved :: MIT License
Classifier: Operating System :: OS Independent
Classifier: Programming Language :: Python :: 3
Classifier: Programming Language :: Python :: 3.8
Classifier: Programming Language :: Python :: 3.9
Classifier: Programming Language :: Python :: 3.10
Classifier: Programming Language :: Python :: 3.11
Classifier: Programming Language :: Python :: 3.12
Requires-Python: >=3.8
License-File: LICENSE
Requires-Dist: sqlmodel
Requires-Dist: sqlalchemy
Requires-Dist: pydantic
Requires-Dist: sqlalchemy-utils
Requires-Dist: sqlalchemy-json
Requires-Dist: python-dotenv
Requires-Dist: pytz
Provides-Extra: all
Requires-Dist: mysql-connector-python ; extra == 'all'
Requires-Dist: pg8000 ; extra == 'all'
Provides-Extra: mysql
Requires-Dist: mysql-connector-python ; extra == 'mysql'
Provides-Extra: postgresql
Requires-Dist: pg8000 ; extra == 'postgresql'
Provides-Extra: test
Requires-Dist: pytest ; extra == 'test'
Requires-Dist: pytest-cov ; extra == 'test'
